LICENSE
MANIFEST.in
README.md
requirements.txt
setup.py
django_item_owner_model/__init__.py
django_item_owner_model/admin.py
django_item_owner_model/apps.py
django_item_owner_model/models.py
django_item_owner_model/tests.py
django_item_owner_model/views.py
django_item_owner_model.egg-info/PKG-INFO
django_item_owner_model.egg-info/SOURCES.txt
django_item_owner_model.egg-info/dependency_links.txt
django_item_owner_model.egg-info/not-zip-safe
django_item_owner_model.egg-info/requires.txt
django_item_owner_model.egg-info/top_level.txt
django_item_owner_model/locale/zh_Hans/LC_MESSAGES/django.mo
django_item_owner_model/locale/zh_Hans/LC_MESSAGES/django.po
django_item_owner_model/migrations/__init__.py