Metadata-Version: 2.1
Name: django-item-owner-model
Version: 0.3.1
Summary: Data item has owner and can be shared to other users. Login user can only see owned or shared data items. User with permit_all permission can see all data items.
Home-page: https://github.com/zencore-cn/zencore-issues
Author: zencore
Author-email: dobetter@zencore.cn
License: MIT
Keywords: django-item-owner-model
Platform: UNKNOWN
Classifier: Development Status :: 5 - Production/Stable
Classifier: Intended Audience :: Developers
Classifier: Topic :: Software Development :: Libraries :: Python Modules
Classifier: License :: OSI Approved :: MIT License
Classifier: Programming Language :: Python :: 3
Classifier: Programming Language :: Python :: 3 :: Only
